README.txt
ogs/CMakeLists.txt
ogs/config.py
ogs/__init__.py
ogs/callbacks.cpython-310-darwin.so
ogs/OGSMesh.cpython-310-darwin.so
ogs/mpl.cpython-310-darwin.so
ogs/OGSSimulator.cpython-310-darwin.so
ogs/_internal/binaries_list.py
ogs/_internal/__init__.py
ogs/_internal/wrap_cli_tools.py
ogs/_internal/get_bin_dir.py
ogs/_internal/provide_ogs_cli_tools_via_wheel.py
ogs/dev/ogs_log_summary.py
ogs-6.5.7.dist-info/RECORD
ogs-6.5.7.dist-info/WHEEL
ogs-6.5.7.dist-info/entry_points.txt
ogs-6.5.7.dist-info/METADATA
ogs-6.5.7.dist-info/licenses/LICENSE.txt
bin/TecPlotTools
bin/createNeumannBc
bin/MoveGeometry
bin/GocadSGridReader
bin/pvtu2vtu
bin/MoveMesh
bin/Mesh2Raster
bin/Raster2ASC
bin/ipDataToPointCloud
bin/RemoveUnusedPoints
bin/mergeMeshToBulkMesh
bin/GMSH2OGS
bin/createLayeredMeshFromRasters
bin/addDataToRaster
bin/generateStructuredMesh
bin/generateGeometry
bin/convertToLinearMesh
bin/PVD2XDMF
bin/createRaster
bin/appendLinesAlongPolyline
bin/MapGeometryToMeshSurface
bin/AddElementQuality
bin/checkMesh
bin/convertGEO
bin/Layers2Grid
bin/editMaterialID
bin/apply_xmlpatch
bin/OpenGeoSysNum.xsd
bin/removeMeshElements
bin/OpenGeoSysProject.xsd
bin/AssignRasterDataToMesh
bin/OpenGeoSysSTN.xsd
bin/createMeshElemPropertiesFromASCRaster
bin/createIntermediateRasters
bin/swapNodeCoordinateAxes
bin/mpmetis
bin/ExtractSurface
bin/createTetgenSmeshFromRasters
bin/geometryToGmshGeo
bin/vtkdiff
bin/identifySubdomains
bin/NodeReordering
bin/ExtractBoundary
bin/CreateAnchors
bin/GocadTSurfaceReader
bin/computeSurfaceNodeIDsInPolygonalRegion
bin/CreateBoundaryConditionsAlongPolylines
bin/IntegrateBoreholesIntoMesh
bin/constructMeshesFromGeometry
bin/queryMesh
bin/scaleProperty
bin/AddFaultToVoxelGrid
bin/convertVtkDataArrayToVtkDataArray
bin/xdmfdiff
bin/RemoveGhostData
bin/ExtractMaterials
bin/ComputeNodeAreasFromSurfaceMesh
bin/Vtu2Grid
bin/MeshMapping
bin/partmesh
bin/VTK2TIN
bin/VTK2OGS
bin/OGS2VTK
bin/postLIE
bin/AddLayer
bin/OpenGeoSysGLI.xsd
bin/reviseMesh
bin/createQuadraticMesh
bin/generateMatPropsFromMatID
bin/OpenGeoSysCND.xsd
bin/TIN2VTK
