Metadata-Version: 2.2
Name: ogs
Version: 6.5.7
Summary: OpenGeoSys Python wheel
Author: OpenGeoSys Community
Author-Email: Unknown <info@opengeosys.org>
License: Copyright (c) 2012-2026, OpenGeoSys Community (http://www.opengeosys.org)
Project-URL: homepage, https://opengeosys.org
Project-URL: documentation, https://www.opengeosys.org/docs
Project-URL: repository, https://gitlab.opengeosys.org/ogs/ogs
Project-URL: changelog, https://gitlab.opengeosys.org/ogs/ogs/-/blob/master/CHANGELOG.md
Requires-Python: >=3.10
Requires-Dist: pandas
